acvsn_checker/__init__.py
acvsn_checker/checker.py
acvsn_checker/data/aerosol_vocab.json
acvsn_checker/data/cloud_vocab.json
acvsn_checker/data/config.json
acvsn_checker/data/gas_vocab.json
acvsn_checker/data/meteorology_vocab.json
acvsn_checker/data/photolysis_rate_vocab.json
acvsn_checker/data/platform_vocab.json
acvsn_checker/data/radiation_vocab.json
tests/__init__.py
tests/test_checker.py
acvsn_checker-0.1.5.dist-info/LICENSE
acvsn_checker-0.1.5.dist-info/METADATA
acvsn_checker-0.1.5.dist-info/WHEEL
acvsn_checker-0.1.5.dist-info/entry_points.txt
acvsn_checker-0.1.5.dist-info/top_level.txt
acvsn_checker-0.1.5.dist-info/RECORD
