Metadata-Version: 2.1
Name: acvsn-checker
Version: 0.1.5
Summary: Checks if a standard name follows the ACVSN conventions
Requires-Python: >=3.4
License-File: LICENSE
Requires-Dist: click (>=8.0.0)
